python3_capsolver/__init__.py
python3_capsolver/__version__.py
python3_capsolver/aws_waf.py
python3_capsolver/cloudflare.py
python3_capsolver/control.py
python3_capsolver/datadome_slider.py
python3_capsolver/friendly_captcha.py
python3_capsolver/gee_test.py
python3_capsolver/image_to_text.py
python3_capsolver/mt_captcha.py
python3_capsolver/recaptcha.py
python3_capsolver/vision_engine.py
python3_capsolver/yandex.py
python3_capsolver/core/__init__.py
python3_capsolver/core/aio_captcha_instrument.py
python3_capsolver/core/base.py
python3_capsolver/core/captcha_instrument.py
python3_capsolver/core/const.py
python3_capsolver/core/context_instr.py
python3_capsolver/core/enum.py
python3_capsolver/core/serializer.py
python3_capsolver/core/sio_captcha_instrument.py
python3_capsolver/core/utils.py
python3_capsolver-1.1.0.dist-info/licenses/LICENSE
python3_capsolver-1.1.0.dist-info/METADATA
python3_capsolver-1.1.0.dist-info/WHEEL
python3_capsolver-1.1.0.dist-info/top_level.txt
python3_capsolver-1.1.0.dist-info/RECORD
