Metadata-Version: 2.4
Name: python3-capsolver
Version: 1.1.0
Summary: Python 3.8+ Capsolver library with AIO module.
Author-email: AndreiDrang <python-captcha@pm.me>
License: MIT License
Project-URL: Homepage, https://andreidrang.github.io/python3-capsolver/
Project-URL: Documentation, https://andreidrang.github.io/python3-capsolver/
Project-URL: Repository, https://github.com/AndreiDrang/python3-capsolver
Project-URL: Issues, https://github.com/AndreiDrang/python3-capsolver/issues
Project-URL: Changelog, https://github.com/AndreiDrang/python3-capsolver/releases
Keywords: captcha,recaptcha,geetest,hcaptcha,capypuzzle,rotatecaptcha,funcaptcha,keycaptcha,python3,python-library,capsolver,datadomeslider,datadome,mtcaptcha,turnstile,cloudflare,amazon,amazon_waf,akamai,imperva,binance
Classifier: License :: OSI Approved :: MIT License
Classifier: License :: OSI Approved :: Mozilla Public License 2.0 (MPL 2.0)
Classifier: Development Status :: 5 - Production/Stable
Classifier: Programming Language :: Python
Classifier: Programming Language :: Python :: 3
Classifier: Programming Language :: Python :: 3 :: Only
Classifier: Programming Language :: Python :: 3.8
Classifier: Programming Language :: Python :: 3.9
Classifier: Programming Language :: Python :: 3.10
Classifier: Programming Language :: Python :: 3.11
Classifier: Programming Language :: Python :: 3.12
Classifier: Framework :: AsyncIO
Classifier: Operating System :: Unix
Classifier: Operating System :: Microsoft :: Windows
Classifier: Operating System :: MacOS
Requires-Python: >=3.8
License-File: LICENSE
Requires-Dist: requests>=2.21.0
Requires-Dist: aiohttp>=3.9.2
Requires-Dist: msgspec<0.20,>=0.18
Requires-Dist: tenacity<10,>=8
Dynamic: license-file
